kmailbox.py
kmailbox-0.2.3.dist-info/METADATA
kmailbox-0.2.3.dist-info/WHEEL
kmailbox-0.2.3.dist-info/entry_points.txt
kmailbox-0.2.3.dist-info/top_level.txt
kmailbox-0.2.3.dist-info/RECORD
