Metadata-Version: 2.1
Name: kmailbox
Version: 0.2.3
Summary: Python email utils
Home-page: https://github.com/kuanghy/kmailbox
Author: Huoty
Author-email: sudohuoty@163.com
Maintainer: Huoty
Maintainer-email: sudohuoty@163.com
License: Apache License v2
Keywords: email,mailbox,smtp,imap,sendmail
Platform: UNKNOWN
Classifier: Programming Language :: Python
Classifier: Programming Language :: Python :: 2.7
Classifier: Programming Language :: Python :: 3.6
Classifier: Programming Language :: Python :: 3.7
Classifier: Programming Language :: Python :: 3.8
Classifier: Programming Language :: Python :: 3.9
Classifier: Operating System :: Unix
Classifier: Operating System :: Microsoft :: Windows
Requires-Python: >=2.7
